odoo/addons/sale_order_import_ubl/README.rst
odoo/addons/sale_order_import_ubl/__init__.py
odoo/addons/sale_order_import_ubl/__manifest__.py
odoo/addons/sale_order_import_ubl/demo/demo_data.xml
odoo/addons/sale_order_import_ubl/i18n/es.po
odoo/addons/sale_order_import_ubl/i18n/it.po
odoo/addons/sale_order_import_ubl/i18n/sale_order_import_ubl.pot
odoo/addons/sale_order_import_ubl/readme/CONTRIBUTORS.md
odoo/addons/sale_order_import_ubl/readme/CREDITS.md
odoo/addons/sale_order_import_ubl/readme/DESCRIPTION.md
odoo/addons/sale_order_import_ubl/readme/USAGE.md
odoo/addons/sale_order_import_ubl/static/description/icon.png
odoo/addons/sale_order_import_ubl/static/description/index.html
odoo/addons/sale_order_import_ubl/tests/__init__.py
odoo/addons/sale_order_import_ubl/tests/common.py
odoo/addons/sale_order_import_ubl/tests/test_ubl_order_import.py
odoo/addons/sale_order_import_ubl/tests/files/UBL-Order-2.0-Example.xml
odoo/addons/sale_order_import_ubl/tests/files/UBL-Order-2.1-Example.xml
odoo/addons/sale_order_import_ubl/tests/files/UBL-RequestForQuotation-2.0-Example.xml
odoo/addons/sale_order_import_ubl/tests/files/UBL-RequestForQuotation-2.1-Example.xml
odoo/addons/sale_order_import_ubl/wizard/__init__.py
odoo/addons/sale_order_import_ubl/wizard/sale_order_import.py
odoo_addon_sale_order_import_ubl-18.0.1.0.1.dist-info/METADATA
odoo_addon_sale_order_import_ubl-18.0.1.0.1.dist-info/WHEEL
odoo_addon_sale_order_import_ubl-18.0.1.0.1.dist-info/top_level.txt
odoo_addon_sale_order_import_ubl-18.0.1.0.1.dist-info/RECORD
