Metadata-Version: 2.1
Name: odoo-addon-sale_order_import_ubl
Version: 18.0.1.0.1
Requires-Python: >=3.10
Requires-Dist: odoo-addon-base_ubl_parse==18.0.*
Requires-Dist: odoo-addon-sale_order_import==18.0.*
Requires-Dist: odoo==18.0.*
Summary: Import UBL XML sale order files
Home-page: https://github.com/OCA/edi
License: AGPL-3
Author: Akretion,Camptocamp,Odoo Community Association (OCA)
Author-email: support@odoo-community.org
Classifier: Programming Language :: Python
Classifier: Framework :: Odoo
Classifier: Framework :: Odoo :: 18.0
Classifier: License :: OSI Approved :: GNU Affero General Public License v3
